ray_launcher/__init__.py
ray_launcher/base_local_module.py
ray_launcher/cluster_launcher.py
ray_launcher/cluster_status_manager.py
ray_launcher/remote_module.py
ray_launcher/utils.py
ray_launcher-1.2.0.dist-info/LICENSE
ray_launcher-1.2.0.dist-info/METADATA
ray_launcher-1.2.0.dist-info/WHEEL
ray_launcher-1.2.0.dist-info/top_level.txt
ray_launcher-1.2.0.dist-info/RECORD
